setup.py
betterurl/__init__.py
betterurl.egg-info/PKG-INFO
betterurl.egg-info/SOURCES.txt
betterurl.egg-info/dependency_links.txt
betterurl.egg-info/top_level.txt
betterurl.egg-info/zip-safe