Metadata-Version: 1.1
Name: betterurl
Version: 0.1.0
Summary: A better URL manipulation library
Home-page: https://github.com/allancaffee/betterurl
Author: Allan Caffee
Author-email: allan.caffee@gmail.com
License: BSD
Keywords: URL
Platform: UNKNOWN
Classifier: Development Status :: 2 - Pre-Alpha
Classifier: Intended Audience :: Developers
Classifier: License :: OSI Approved :: BSD License
Classifier: Operating System :: MacOS :: MacOS X
Classifier: Operating System :: POSIX
Classifier: Programming Language :: Python
